MANIFEST.in
setup.py
gsignals/__init__.py
gsignals/signals.py
gsignals/util.py
gsignals/weak.py
gsignals.egg-info/PKG-INFO
gsignals.egg-info/SOURCES.txt
gsignals.egg-info/dependency_links.txt
gsignals.egg-info/not-zip-safe
gsignals.egg-info/top_level.txt
tests/test_gobject_gc.py
tests/test_signals.py