Metadata-Version: 1.0
Name: gsignals
Version: 0.1
Summary: Wrappers for gobject signals
Home-page: http://github.com/baverman/scribes-goodies
Author: Anton Bobrov
Author-email: bobrov@vl.ru
License: UNKNOWN
Platform: UNKNOWN
